Metadata-Version: 2.1
Name: TeleAuto
Version: 0.0.2
Summary: tele's auto
Home-page: https://github.com/hikkki/py-try
Author: yxq
Author-email: yunyxq@163.com
License: MIT
Platform: any
